adlinkusb/__init__.py
adlinkusb/daq7250.py
adlink_usb-0.0.1.dist-info/LICENSE
adlink_usb-0.0.1.dist-info/METADATA
adlink_usb-0.0.1.dist-info/WHEEL
adlink_usb-0.0.1.dist-info/top_level.txt
adlink_usb-0.0.1.dist-info/RECORD
